mk312/__init__.py
mk312/__version__.py
mk312/com.py
mk312/constants.py
mk312/exceptions.py
mk312/utils.py
mk312-0.4.3.dist-info/LICENSE
mk312-0.4.3.dist-info/METADATA
mk312-0.4.3.dist-info/WHEEL
mk312-0.4.3.dist-info/top_level.txt
mk312-0.4.3.dist-info/RECORD
