Metadata-Version: 2.1
Name: mk312
Version: 0.4.3
Summary: MK312 Communication Wrapper.
Home-page: https://github.com/Rubberfate/mk312com
Author: Rubberfate
Author-email: rubberfate@gmail.com
License: MIT
Platform: UNKNOWN
Classifier: License :: OSI Approved :: MIT License
Classifier: Programming Language :: Python
Classifier: Programming Language :: Python :: 3
Classifier: Programming Language :: Python :: 3.6
Classifier: Programming Language :: Python :: Implementation :: CPython
Classifier: Programming Language :: Python :: Implementation :: PyPy
Requires-Python: >=3.6.0
License-File: LICENSE
Requires-Dist: pyserial
